logstream/__init__.py
logstream/__main__.py
logstream/logstream.py
logstream-1.0.0.dist-info/METADATA
logstream-1.0.0.dist-info/WHEEL
logstream-1.0.0.dist-info/entry_points.txt
logstream-1.0.0.dist-info/top_level.txt
logstream-1.0.0.dist-info/RECORD
